{
  "orchestrationId": "orchestration-2025-12-11T12-17-18-295Z-ff3435032c8b",
  "environment": "production",
  "startTime": "2025-12-11T12:17:18.295Z",
  "endTime": null,
  "summary": {
    "orchestrationId": "orchestration-2025-12-11T12-17-18-295Z-ff3435032c8b",
    "environment": "production",
    "totalDomains": 0,
    "completed": 0,
    "failed": 0,
    "inProgress": 0,
    "pending": 0,
    "startTime": "2025-12-11T12:17:18.295Z",
    "endTime": null,
    "duration": 154,
    "auditLogSize": 2
  },
  "domainStates": {},
  "rollbackPlan": [],
  "auditLog": [
    {
      "timestamp": "2025-12-11T12:17:18.341Z",
      "orchestrationId": "orchestration-2025-12-11T12-17-18-295Z-ff3435032c8b",
      "event": "PORTFOLIO_INITIALIZED",
      "domain": "ALL",
      "details": {
        "totalDomains": 0,
        "domains": []
      },
      "sequenceNumber": 1
    },
    {
      "timestamp": "2025-12-11T12:17:18.449Z",
      "orchestrationId": "orchestration-2025-12-11T12-17-18-295Z-ff3435032c8b",
      "event": "orchestrator_initialized",
      "domain": {
        "domains": [],
        "environment": "production",
        "modularComponents": [
          "DomainResolver",
          "DeploymentCoordinator",
          "StateManager"
        ]
      },
      "details": {},
      "sequenceNumber": 2
    }
  ],
  "metadata": {
    "dryRun": false,
    "persistenceEnabled": true,
    "rollbackEnabled": true
  }
}